azql/__init__.py
azql/convert.py
azql/utils.py
azql/cli/__init__.py
azql/cli/formatter.py
azql/cli/parser.py
azql/cli/commands/__init__.py
azql/cli/commands/convert.py
azql/config/__init__.py
azql/core/__init__.py
azql/core/convert_types.py
azql/core/detect.py
azql/core/generate_ddl.py
azql/core/models.py
azql/core/styles.py
azql/core/validate.py
azql/core/dialects/__init__.py
azql/core/dialects/mysql.py
azql/core/dialects/postgresql.py
azql/core/dialects/tsql.py
azql/io/__init__.py
azql/io/read.py
azql-0.1.3.dist-info/METADATA
azql-0.1.3.dist-info/WHEEL
azql-0.1.3.dist-info/entry_points.txt
azql-0.1.3.dist-info/licenses/LICENSE
azql-0.1.3.dist-info/RECORD
