Metadata-Version: 2.4
Name: azql
Version: 0.1.3
Summary: AZQL is a tool for converting data files (CSV, JSON) to SQL DDL (Data Definition Language) scripts.
Author-email: Markus Feiks <pypi.packages@feyx.de>
License:                     GNU GENERAL PUBLIC LICENSE
License-File: LICENSE
Requires-Python: >=3.11
